TDTNex/QRS_tools.py
TDTNex/TDTNexReader.py
TDTNex/__init__.py
tdtnex-0.4.10.dist-info/licenses/LICENSE
tdtnex-0.4.10.dist-info/METADATA
tdtnex-0.4.10.dist-info/WHEEL
tdtnex-0.4.10.dist-info/top_level.txt
tdtnex-0.4.10.dist-info/RECORD
