Metadata-Version: 2.4
Name: TDTNex
Version: 0.4.10
Summary: To add OfflineSorter codes to TDT blocks
Author-email: Matthew Perkins <matthew.perkins@mssm.edu>
Project-URL: Homepage, https://github.com/matthewperkins/TDTNex
Project-URL: Bug Tracker, https://github.com/matthewperkins/TDTNex/issues
Classifier: 
Requires-Python: >=3.7
License-File: LICENSE
Requires-Dist: pandas
Requires-Dist: numpy
Requires-Dist: opencv-python
Requires-Dist: numba
Requires-Dist: matplotlib
Requires-Dist: tdt
Dynamic: license-file
